CraftiGames/__JartexNetwork__.py
CraftiGames/__PikaNetwork__.py
CraftiGames/__init__.py
CraftiGames/utils.py
CraftiGames/Games/Bedwars.py
CraftiGames/Games/Practice.py
CraftiGames/Games/Skywars.py
CraftiGames/Games/__init__.py
CraftiGames/Punishments/__init__.py
CraftiGames/Ratelimits/JartexNetworkRateLimitHandler.py
CraftiGames/Ratelimits/PikaNetworkRateLimitHandler.py
CraftiGames/Ratelimits/__init__.py
CraftiGames/RefactorAPI/Guilds.py
CraftiGames/RefactorAPI/Leaderboard.py
CraftiGames/RefactorAPI/NetworkStatus.py
CraftiGames/RefactorAPI/Profiles.py
CraftiGames/RefactorAPI/Recaps.py
CraftiGames/RefactorAPI/__init__.py
CraftiGames/ResponseError/__init__.py
CraftiGames/Skins/__init__.py
CraftiGames/_Logger/__init__.py
CraftiGames.py-2.1.1.dist-info/LICENSE
CraftiGames.py-2.1.1.dist-info/METADATA
CraftiGames.py-2.1.1.dist-info/WHEEL
CraftiGames.py-2.1.1.dist-info/top_level.txt
CraftiGames.py-2.1.1.dist-info/RECORD
